taxon2wikipedia/__init__.py
taxon2wikipedia/cli.py
taxon2wikipedia/create_taxon_on_wikidata.py
taxon2wikipedia/helper.py
taxon2wikipedia/render_page.py
taxon2wikipedia/data/full_query_taxon.rq.jinja
tests/test_render_page.py
taxon2wikipedia-0.1.0.dist-info/LICENSE
taxon2wikipedia-0.1.0.dist-info/METADATA
taxon2wikipedia-0.1.0.dist-info/WHEEL
taxon2wikipedia-0.1.0.dist-info/entry_points.txt
taxon2wikipedia-0.1.0.dist-info/top_level.txt
taxon2wikipedia-0.1.0.dist-info/RECORD
