Metadata-Version: 2.1
Name: taxon2wikipedia
Version: 0.1.0
Summary: Add taxa stubs to Wikipedia
License: MIT
License-File: LICENSE
Requires-Dist: wdcuration
Requires-Dist: clipboard
Requires-Dist: requests
Requires-Dist: SPARQLWrapper
Requires-Dist: click
Requires-Dist: beautifulsoup4
Requires-Dist: pywikibot
Requires-Dist: mwparserfromhell
Requires-Dist: wikidata2df
Provides-Extra: tests
Requires-Dist: pytest; extra == "tests"
